easyFlyTracker/__init__.py
easyFlyTracker/__main__.py
easyFlyTracker/cli.py
easyFlyTracker/fonts/times.ttf
easyFlyTracker/fonts/timesbd.ttf
easyFlyTracker/fonts/timesbi.ttf
easyFlyTracker/fonts/timesi.ttf
easyFlyTracker/src_code/Camera_Calibration.py
easyFlyTracker/src_code/SignificanceTest.py
easyFlyTracker/src_code/__init__.py
easyFlyTracker/src_code/analysis.py
easyFlyTracker/src_code/fly_angle.py
easyFlyTracker/src_code/fly_seg.py
easyFlyTracker/src_code/gui_config.py
easyFlyTracker/src_code/kernel_density_estimation.py
easyFlyTracker/src_code/load_configyaml.py
easyFlyTracker/src_code/log_about.py
easyFlyTracker/src_code/show.py
easyFlyTracker/src_code/utils.py
easyFlyTracker-0.14.2.dist-info/LICENSE
easyFlyTracker-0.14.2.dist-info/METADATA
easyFlyTracker-0.14.2.dist-info/WHEEL
easyFlyTracker-0.14.2.dist-info/entry_points.txt
easyFlyTracker-0.14.2.dist-info/top_level.txt
easyFlyTracker-0.14.2.dist-info/RECORD
