Metadata-Version: 2.1
Name: easyFlyTracker
Version: 0.14.2
Summary: An easy-to-use program for analyzing Drosophila Activity.
Home-page: https://github.com/azzhu/EasyFlyTracker
Author: azzhu
Author-email: zhu.qingjie@qq.com
License: MIT
Project-URL: Source Code, https://github.com/azzhu/EasyFlyTracker
Project-URL: Bug Tracker, https://github.com/azzhu/EasyFlyTracker/issues
Classifier: Programming Language :: Python :: 3
Classifier: License :: OSI Approved :: MIT License
Classifier: Operating System :: OS Independent
Requires-Python: >=3
License-File: LICENSE
Requires-Dist: seaborn
Requires-Dist: moviepy
Requires-Dist: opencv-python
Requires-Dist: opencv-utf-8
Requires-Dist: scipy
Requires-Dist: pandas
Requires-Dist: numpy
Requires-Dist: matplotlib
Requires-Dist: PyYAML
Requires-Dist: openpyxl
Requires-Dist: scikit-learn
Requires-Dist: loguru
Requires-Dist: psutil
